{
  "trades": [
    {
      "timestamp": "2026-01-12T22:11:30.504462",
      "market_slug": "btc-updown-15m-1768226400",
      "price_up": 0.64,
      "price_down": 0.35,
      "total_cost": 0.99,
      "order_size": 5.0,
      "total_investment": 4.95,
      "expected_payout": 5.0,
      "expected_profit": 0.04999999999999982,
      "profit_percentage": 1.0101010101010066,
      "order_ids": [],
      "filled": true,
      "market_result": null,
      "actual_profit": null
    },
    {
      "timestamp": "2026-01-12T22:49:15.120162",
      "market_slug": "btc-updown-15m-1768229100",
      "price_up": 0.49,
      "price_down": 0.5,
      "total_cost": 0.99,
      "order_size": 5.0,
      "total_investment": 4.95,
      "expected_payout": 5.0,
      "expected_profit": 0.04999999999999982,
      "profit_percentage": 1.0101010101010066,
      "order_ids": [],
      "filled": true,
      "market_result": null,
      "actual_profit": null
    }
  ],
  "start_time": "2026-01-12T22:04:16.622514"
}